othpc/__init__.py
othpc/submit_function.py
othpc/utils.py
othpc/example/__init__.py
othpc/example/cantilever_beam/cantilever_beam.py
othpc/example/cantilever_beam/run_doe.py
othpc/example/cantilever_beam/run_form.py
othpc/example/cantilever_beam/run_fromalgo.py
othpc/example/cantilever_beam/run_withcache.py
othpc/example/cantilever_beam/template/LICENCE.xml
othpc/example/cantilever_beam/template/beam
othpc/example/cantilever_beam/template/beam_input_template.xml
othpc/example/cantilever_beam/template/beam_old
othpc/example/code_aster/runCA.py
othpc/example/load_simulator/MPILoadSimulator.py
othpc/example/load_simulator/run_cronos.py
othpc/example/warren_truss_structure/run_cronos.py
othpc/example/warren_truss_structure/truss_fem_model.py
othpc/example/warren_truss_structure/truss_plot.py
othpc-0.1.dist-info/COPYING
othpc-0.1.dist-info/COPYING.LESSER
othpc-0.1.dist-info/METADATA
othpc-0.1.dist-info/WHEEL
othpc-0.1.dist-info/top_level.txt
othpc-0.1.dist-info/RECORD
