Metadata-Version: 2.1
Name: othpc
Version: 0.1
Summary: Simplifies the evaluation of numerical simulation models on high performance computing facilities
Author: Elias Fekhari, Joseph Muré, Michaël Baudin
License: LGPL-3.0-or-later
Classifier: Environment :: Console
Classifier: Intended Audience :: Science/Research
Classifier: Intended Audience :: Developers
Classifier: Natural Language :: English
Classifier: Programming Language :: Python :: 3
Classifier: Topic :: Software Development
Classifier: Topic :: Scientific/Engineering
License-File: COPYING
License-File: COPYING.LESSER
Requires-Dist: openturns
Requires-Dist: packaging
Requires-Dist: pandas
Requires-Dist: setuptools
Requires-Dist: submitit
Requires-Dist: tqdm
Provides-Extra: doc
Requires-Dist: numpydoc ; extra == 'doc'
Requires-Dist: sphinx ; extra == 'doc'
Requires-Dist: sphinx-gallery ; extra == 'doc'
